tdownloader/__init__.py
tdownloader/downloader.py
tdownloader/input_file_reader.py
tdownloader/main.py
test/__init__.py
test/conftest.py
test/test_downloader.py
tdownloader-1.0.0a0.post1.dist-info/METADATA
tdownloader-1.0.0a0.post1.dist-info/WHEEL
tdownloader-1.0.0a0.post1.dist-info/entry_points.txt
tdownloader-1.0.0a0.post1.dist-info/top_level.txt
tdownloader-1.0.0a0.post1.dist-info/RECORD
