Metadata-Version: 2.1
Name: tdownloader
Version: 1.0.0a0.post1
Summary: Download media shared through some telegram groups.
Home-page: UNKNOWN
Author: Raydel Miranda Gomez
Author-email: raydel.miranda.gomez@gmail.com
License: UNKNOWN
Platform: UNKNOWN
Requires-Dist: requests
Requires-Dist: tqdm
